<?xml version="1.0" encoding="UTF-8"?>
<Subscription xmlns="http://schemas.microsoft.com/2006/03/windows/events/subscription">
    <SubscriptionId>Windows PowerShell - Script Block Tracing (v5+)</SubscriptionId>
    <SubscriptionType>SourceInitiated</SubscriptionType>
    <Description>Provides visibility of all PowerShell execution (version 5+)</Description>
    <Enabled>false</Enabled>
    <Uri>http://schemas.microsoft.com/wbem/wsman/1/windows/EventLog</Uri>
    <ConfigurationMode>MinLatency</ConfigurationMode>
    <Query><![CDATA[
<QueryList>
  <Query Id="0" Path="Microsoft-Windows-PowerShell/Operational">
    <!-- Selects PowerShell 'Script Block Tracing' (4104), PowerShell 5+ -->
    <Select Path="Microsoft-Windows-PowerShell/Operational">*[System[EventID=4104]]</Select>
    <Suppress Path="Microsoft-Windows-PowerShell/Operational">
           <!-- Suppress common system activity -->
            *[EventData[Data[@Name='ScriptBlockText']='prompt']] or
            *[EventData[Data[@Name='ScriptBlockText']='$global:?']]
    </Suppress>
  </Query>
</QueryList>
]]>
    </Query>
    <ReadExistingEvents>true</ReadExistingEvents>
    <TransportName>HTTP</TransportName>
    <ContentFormat>Events</ContentFormat>
    <Locale Language="en-US"/>
    <LogFile>ForwardedEvents</LogFile>
    <PublisherName>Microsoft-Windows-EventCollector</PublisherName>
    <AllowedSourceNonDomainComputers>
        <AllowedIssuerCAList>
        </AllowedIssuerCAList>
    </AllowedSourceNonDomainComputers>
    <AllowedSourceDomainComputers></AllowedSourceDomainComputers>
</Subscription>
